{
	"id": 12345678901,
	"creationDate": "2021-09-29T08:30:00Z",
	"creationUser": "OGBP4399",
	"creationUserFirstName": "John",
	"creationUserSurname": "Smith",
	"ADRcountryCode": "GB",
	"brand": "EP",
	"insuranceType": "COI",
	"insuranceOptions": "",
	"contractId": "",
	"contractStatus": "",
	"claim": {
		"claimNumber": "21-02088761",
		"createdBy": "RisKAppli Interface",
		"status": "New",
		"substatus": "",
		"assessment": "Claimable",
		"insuranceType": "COI",
		"claimType": "Own Damage",
		"subType": "Coroprate",
		"claimOrigin": "ADR",
		"repaired": True,
		"externalReferenceNumberRequired":False,
		"externelReferenceNumber": "",
		"complete": True,
		"numberOfUnsignedDamage": 1,
		
	},
	"rentalAgreement": {
		"COStationCode": "LPLC01",
		"CIStationCode": "LPLC01",
		"COStationName": "Liverpool City",
		"CIStationName": "Liverpool City",
		"CODate": "2021-08-11T08:30:00Z",
		"CIDate": "2021-09-04T08:30:00Z",
		"insuranceOptinTaken": "COI;COI-LDO;LAF"
	},
	"vehicle": {
		"registrationNumber": "AJGGRG",
		"makeCode": "VW",
		"makeName": "Volkswagen",
		"modelDescription": "VW ARTEON 2.0 R-LINE TDI 150PS DSG",
		"vehicleRegistrationDate": "2021-05-29T08:30:00Z",
		"vehicleChassisNumber": "WVWZZZ3HZME005354"
	},
	"accident": {
		"incidentCode": "EV",
		"incidentDescription": "DAMAGE TO EC VEHICLE, NO OTHER DAMAGE",
		"status": "C",
		"date": "2021-01-30T08:30:00Z",
		},
	"damage": [{
			"sequence": "3292258",
			"areaDescription": "Mechanical",
			"elementDescription": "Cooling unit",
			"severityCode": "0",
			"ElementCode":"557",
			"areaCode": "MEC",
			"severityDescription": "Broken",
			"acknowledgment": "CNP"
	},
		{
			"sequence": "3292258",
			"areaDescription": "Mechanical",
			"elementDescription": "Cooling unit",
			"severityCode": "0",
			"ElementCode":"557",
			"areaCode": "MEC",
			"severityDescription": "Broken",
			"acknowledgment": "CNP"
		}
	],
	"driver": {
		"id": 80643859,
		"firstName": "Beatrice",
		"lastName": "Fontaine",
		"licenseNumber": "123456ffff",
		"email": "beatrice.fontaine@europcar.com"
	}
}
